mvlearnPanorama/__init__.py
mvlearnPanorama/Cluster/__init__.py
mvlearnPanorama/Cluster/basecluster.py
mvlearnPanorama/Cluster/mv_coreg_spectral.py
mvlearnPanorama/Cluster/mv_kmeans.py
mvlearnPanorama/Cluster/mv_kmeans_minibatch.py
mvlearnPanorama/Cluster/mv_spectral.py
mvlearnPanorama/Cluster/mv_spherical_kmeans.py
mvlearnPanorama/Cluster/mv_spherical_kmeans_minibatch.py
mvlearnPanorama-0.0.1.dist-info/METADATA
mvlearnPanorama-0.0.1.dist-info/WHEEL
mvlearnPanorama-0.0.1.dist-info/top_level.txt
mvlearnPanorama-0.0.1.dist-info/RECORD
